fuzidate/__init__.py
fuzidate/fuzidate.py
fuzidate-1.0.0.dist-info/LICENSE
fuzidate-1.0.0.dist-info/METADATA
fuzidate-1.0.0.dist-info/WHEEL
fuzidate-1.0.0.dist-info/top_level.txt
fuzidate-1.0.0.dist-info/RECORD
